[[{"category":"F","counts":1,"description":"OPERATING A MOTOR VEHICLE WHILE UNDER THE INFLUENCE OF ALCOHOL AS AN E FELONY","attempted":"false","agency_code":"VTL 1192(2)"},{"category":"M","counts":1,"description":"OPERATING A MOTOR VEHICLE WHILE UNDER THE INFLUENCE OF ALCOHOL OR DRUGS","attempted":"false","agency_code":"VTL 1192(3)"},{"category":"V","counts":1,"description":"DISORDERLY CONDUCT","attempted":"false","agency_code":"PL 240.20(5)"},{"category":"V","counts":1,"description":"CONSUMPTION OF ALCOHOL IN PUBLIC","attempted":"false","agency_code":"AC 10-125(B)"},{"category":"I","counts":1,"description":"OPERATING A MOTOR VEHICLE WHILE UNDER THE INFLUENCE OF ALCOHOL OR DRUGS","attempted":"false","agency_code":"VTL 1192(1)"}],[{"category":"F","counts":2,"description":"CRIMINAL POSSESSION OF A WEAPON IN THE THIRD DEGREE (DQO)","attempted":"false","agency_code":"PL 265.02(1)"},{"category":"M","counts":2,"description":"CRIMINAL POSSESSION OF A WEAPON IN THE FOURTH DEGREE","attempted":"false","agency_code":"PL 265.01(1)"}],[{"category":"F","counts":1,"description":"AGGRAVATED UNLICENSED OPERATION OF A MOTOR VEHICLE IN THE FIRST DEGREE","attempted":"false","agency_code":"VTL 511(3)(A)(I)"},{"category":"M","counts":1,"description":"OPERATING A MOTOR VEHICLE WHILE UNDER THE INFLUENCE OF ALCOHOL OR DRUGS","attempted":"false","agency_code":"VTL 1192(2)"},{"category":"M","counts":1,"description":"OPERATING A MOTOR VEHICLE WHILE UNDER THE INFLUENCE OF ALCOHOL OR DRUGS","attempted":"false","agency_code":"VTL 1192(3)"},{"category":"M","counts":1,"description":"RECKLESS DRIVING","attempted":"false","agency_code":"VTL 1212"},{"category":"I","counts":1,"description":"OPERATING A MOTOR VEHICLE WHILE UNDER THE INFLUENCE OF ALCOHOL OR DRUGS","attempted":"false","agency_code":"VTL 1192(1)"}],[{"category":"M","counts":1,"description":"OPERATING A MOTOR VEHICLE WHILE UNDER THE INFLUENCE OF ALCOHOL OR DRUGS","attempted":"false","agency_code":"VTL 1192(2)"},{"category":"M","counts":1,"description":"OPERATING A MOTOR VEHICLE WHILE UNDER THE INFLUENCE OF ALCOHOL OR DRUGS","attempted":"false","agency_code":"VTL 1192(3)"},{"category":"M","counts":1,"description":"RECKLESS DRIVING","attempted":"false","agency_code":"VTL 1212"},{"category":"V","counts":1,"description":"FAILURE TO GIVE APPROPRIATE SIGNAL TO TURN","attempted":"false","agency_code":"VTL 1163(A)"},{"category":"V","counts":1,"description":"CONSUMPTION OF ALCOHOL IN PUBLIC","attempted":"false","agency_code":"AC 10-125(B)"},{"category":"I","counts":1,"description":"FAILURE TO OBEY TRAFFIC CONTROL SIGNAL","attempted":"false","agency_code":"VTL 1111(D)(1)"},{"category":"I","counts":1,"description":"OPERATING A MOTOR VEHICLE WHILE UNDER THE INFLUENCE OF ALCOHOL OR DRUGS","attempted":"false","agency_code":"VTL 1192(1)"}],[{"category":"F","counts":1,"description":"Criminal Sale of a Controlled Substance in the Third Degree","attempted":"false","agency_code":"PL 220.39(1)"}],[{"category":"F","counts":1,"description":"Criminal Possession of a Controlled Substance in the Third Degree","attempted":"false","agency_code":"PL 220.16(1)"},{"category":"F","counts":1,"description":"Criminal Sale of a Controlled Substance in the Third Degree","attempted":"false","agency_code":"PL 220.39(1)"}],[{"category":"F","counts":1,"description":"Criminal Possession of a Controlled Substance in the Third Degree","attempted":"false","agency_code":"PL 220.16(1)"}],[{"category":"M","counts":1,"description":"Petit Larceny","attempted":"false","agency_code":"PL 155.25"},{"category":"M","counts":1,"description":"Criminal Possession of Stolen Property in the Fifth Degree","attempted":"false","agency_code":"PL 165.40"}],[{"category":"M","counts":1,"description":"Criminal Sale of marijuana in the Fourth Degree","attempted":"false","agency_code":"PL 221.40"},{"category":"M","counts":1,"description":"Criminal Possession of Marijuana in the Fifth Degree - DNA Eligible Only With Prior Conviction","attempted":"false","agency_code":"PL 221.10(1)"},{"category":"V","counts":1,"description":"Unlawful Possession Of Marijuana","attempted":"false","agency_code":"PL 221.05"}],[{"category":"M","counts":1,"description":"Theft of Services","attempted":"false","agency_code":"PL 165.15(3)"}],[{"category":"M","counts":1,"description":"Criminal Possession of a Controlled Substance in the Seventh Degree","attempted":"false","agency_code":"PL 220.03"},{"category":"M","counts":1,"description":"Criminal Possession of Marijuana in the Fifth Degree - DNA Eligible Only With Prior Conviction","attempted":"false","agency_code":"PL 221.10(1)"}],[{"category":"M","counts":1,"description":"Theft of Services","attempted":"false","agency_code":"PL 165.15(3)"},{"category":"M","counts":1,"description":"Criminal Trespass in the Third Degree","attempted":"false","agency_code":"PL 140.10(a)"}],[{"category":"M","counts":1,"description":"Criminal Trespass in the Second Degree","attempted":"false","agency_code":"PL 140.15(1)"},{"category":"M","counts":1,"description":"Criminal Possession of a Controlled Substance in the Seventh Degree","attempted":"false","agency_code":"PL 220.03"},{"category":"M","counts":1,"description":"Criminal Trespass in the Third Degree","attempted":"false","agency_code":"PL 140.10(a)"},{"category":"M","counts":1,"description":"Criminal Trespass in the Third Degree","attempted":"false","agency_code":"PL 140.10(e)"}],[{"category":"V","counts":1,"description":"Consumption of Alcohol in a Public Place","attempted":"false","agency_code":"AC 10-125(b)"}],[{"category":"V","counts":1,"description":"Occupying Multiple Seats on a Transit Facility Subway or Bus","attempted":"false","agency_code":"21 NYCRR 1050.7(j)(1)"},{"category":"V","counts":1,"description":"Placing a Foot on a Seat on a MTA Subway or Bus","attempted":"false","agency_code":"21 NYCRR 1050.7(j)(2)"}],[{"category":"M","counts":1,"description":"Criminal Trespass in the Third Degree","attempted":"false","agency_code":"PL 140.10(a)"},{"category":"M","counts":1,"description":"Criminal Possession of Marijuana in the Fifth Degree - DNA Eligible Only With Prior Conviction","attempted":"false","agency_code":"PL 221.10(1)"},{"category":"V","counts":1,"description":"Trespass","attempted":"false","agency_code":"PL 140.05"},{"category":"V","counts":1,"description":"Unlawful Possession Of Marijuana","attempted":"false","agency_code":"PL 221.05"}],[{"category":"M","counts":1,"description":"Criminal Trespass in the Third Degree","attempted":"false","agency_code":"PL 140.10(a)"},{"category":"M","counts":1,"description":"Criminal Possession of Marijuana in the Fifth Degree - DNA Eligible Only With Prior Conviction","attempted":"false","agency_code":"PL 221.10(1)"},{"category":"V","counts":1,"description":"Trespass","attempted":"false","agency_code":"PL 140.05"},{"category":"V","counts":1,"description":"Unlawful Possession Of Marijuana","attempted":"false","agency_code":"PL 221.05"}],[{"category":"M","counts":1,"description":"Criminal Trespass in the Third Degree","attempted":"false","agency_code":"PL 140.10(a)"},{"category":"M","counts":1,"description":"Criminal Possession of Marijuana in the Fifth Degree - DNA Eligible Only With Prior Conviction","attempted":"false","agency_code":"PL 221.10(1)"},{"category":"V","counts":1,"description":"Trespass","attempted":"false","agency_code":"PL 140.05"},{"category":"V","counts":1,"description":"Unlawful Possession Of Marijuana","attempted":"false","agency_code":"PL 221.05"}],[{"category":"M","counts":1,"description":"Attempted Illegal Possession of a Vehicle Identification Number","attempted":"true","agency_code":"PL 110/170.70(2)"}],[{"category":"M","counts":2,"description":"Assault in the Third Degree","attempted":"false","agency_code":"PL 120.00(1)"},{"category":"M","counts":2,"description":"Assault in the Third Degree","attempted":"false","agency_code":"PL 120.00(2)"},{"category":"V","counts":2,"description":"Harassment in the Second Degree","attempted":"false","agency_code":"PL 240.26(1)"}],[{"category":"M","counts":1,"description":"Criminal Possession of Marijuana in the Fifth Degree - DNA Eligible Only With Prior Conviction","attempted":"false","agency_code":"PL 221.10(1)"},{"category":"V","counts":1,"description":"Unlawful Possession Of Marijuana","attempted":"false","agency_code":"PL 221.05"}],[{"category":"M","counts":1,"description":"Unauthorized Use of a Vehicle in the Third Degree","attempted":"false","agency_code":"PL 165.05(1)"}],[{"category":"M","counts":1,"description":"Criminal Trespass in the Second Degree","attempted":"false","agency_code":"PL 140.15(1)"},{"category":"M","counts":1,"description":"Criminal Possession of a Controlled Substance in the Seventh Degree","attempted":"false","agency_code":"PL 220.03"},{"category":"M","counts":1,"description":"Criminal Trespass in the Third Degree","attempted":"false","agency_code":"PL 140.10(a)"}],[{"category":"M","counts":1,"description":"Aggravated Unlicensed Operation of a Motor Vehicle in the Third Degree -Not DNA Eligible","attempted":"false","agency_code":"VTL 511(1)(a)"},{"category":"I","counts":1,"description":"Unlicensed Driving","attempted":"false","agency_code":"VTL 509(1)"}],[{"category":"M","counts":1,"description":"Theft of Services","attempted":"false","agency_code":"PL 165.15(3)"},{"category":"M","counts":1,"description":"Criminal Trespass in the Third Degree","attempted":"false","agency_code":"PL 140.10(a)"}],[{"category":"M","counts":1,"description":"Criminal Possession of Marijuana in the Fifth Degree - DNA Eligible Only With Prior Conviction","attempted":"false","agency_code":"PL 221.10(1)"},{"category":"V","counts":1,"description":"Unlawful Possession Of Marijuana","attempted":"false","agency_code":"PL 221.05"}],[{"category":"M","counts":1,"description":"Theft of Services","attempted":"false","agency_code":"PL 165.15(3)"}],[{"category":"M","counts":1,"description":"Petit Larceny","attempted":"false","agency_code":"PL 155.25"},{"category":"M","counts":1,"description":"Criminal Possession of Stolen Property in the Fifth Degree","attempted":"false","agency_code":"PL 165.40"}],[{"category":"F","counts":1,"description":"Attempted Robbery in the Third Degree","attempted":"true","agency_code":"PL 110/160.05"}],[{"category":"M","counts":1,"description":"Criminal Sale of marijuana in the Fourth Degree","attempted":"false","agency_code":"PL 221.40"},{"category":"M","counts":1,"description":"Criminal Possession of Marijuana in the Fifth Degree - DNA Eligible Only With Prior Conviction","attempted":"false","agency_code":"PL 221.10(1)"},{"category":"V","counts":1,"description":"Unlawful Possession Of Marijuana","attempted":"false","agency_code":"PL 221.05"}],[{"category":"V","counts":1,"description":"Unlawful Possession Of Marijuana","attempted":"false","agency_code":"PL 221.05"}],[{"category":"F","counts":2,"description":"Criminal Possession of a Forged Instrument in the Second Degree","attempted":"false","agency_code":"PL 170.25"}],[{"category":"M","counts":1,"description":"Criminal Trespass in the Second Degree","attempted":"false","agency_code":"PL 140.15(1)"}],[{"category":"M","counts":1,"description":"Criminal Possession of a Controlled Substance in the Seventh Degree","attempted":"false","agency_code":"PL 220.03"}],[{"category":"V","counts":1,"description":"Placing a Foot on a Seat on a MTA Subway or Bus","attempted":"false","agency_code":"21 NYCRR 1050.7(j)(2)"}],[{"category":"M","counts":1,"description":"Aggravated Unlicensed Operation of a Motor Vehicle in the Third Degree -Not DNA Eligible","attempted":"false","agency_code":"VTL 511(1)(a)"},{"category":"M","counts":1,"description":"Aggravated Unlicensed Operation of a Motor Vehicle in the Second Degree - Not DNA Eligible","attempted":"false","agency_code":"VTL 511(2)(a)(iv)"},{"category":"I","counts":1,"description":"Unlicensed Driving","attempted":"false","agency_code":"VTL 509(1)"}],[{"category":"I","counts":1,"description":"Unlicensed Driving","attempted":"false","agency_code":"VTL 509(1)"}],[{"category":"F","counts":6,"description":"Criminal Sale of a Controlled Substance in the Third Degree","attempted":"false","agency_code":"PL 220.39(1)"}],[{"category":"M","counts":1,"description":"Petit Larceny","attempted":"false","agency_code":"PL 155.25"},{"category":"M","counts":1,"description":"Criminal Possession of Stolen Property in the Fifth Degree","attempted":"false","agency_code":"PL 165.40"}],[{"category":"M","counts":1,"description":"Criminal Trespass in the Third Degree","attempted":"false","agency_code":"PL 140.10(a)"}],[{"category":"M","counts":1,"description":"Criminal Possession of a Controlled Substance in the Seventh Degree","attempted":"false","agency_code":"PL 220.03"}],[{"category":"M","counts":1,"description":"Theft of Services","attempted":"false","agency_code":"PL 165.15(3)"},{"category":"M","counts":1,"description":"Criminal Trespass in the Third Degree","attempted":"false","agency_code":"PL 140.10(a)"}],[{"category":"V","counts":1,"description":"Selling Food in the Subway","attempted":"false","agency_code":"21 NYCRR 1050.6(b)(1)"}],[{"category":"M","counts":1,"description":"ASSAULT IN THE THIRD DEGREE (DQO)","attempted":"false","agency_code":"PL 120.00(1)"},{"category":"M","counts":1,"description":"CRIMINAL OBSTRUCTION OF BREATHING OR BLOOD CIRCULATION (DQO)","attempted":"false","agency_code":"PL 121.11(A)"},{"category":"M","counts":1,"description":"ASSAULT IN THE THIRD DEGREE (DQO)","attempted":"true","agency_code":"PL 120.00(1)"},{"category":"M","counts":1,"description":"MENACING IN THE THIRD DEGREE(DQO)","attempted":"false","agency_code":"PL 120.15"},{"category":"V","counts":1,"description":"HARASSMENT IN THE SECOND DEGREE","attempted":"false","agency_code":"PL 240.26(1)"}],[{"category":"F","counts":1,"description":"BURGLARY IN THE FIRST DEGREE (DQO)","attempted":"false","agency_code":"PL 140.30(1)"},{"category":"F","counts":1,"description":"ROBBERY IN THE FIRST DEGREE (DQO)","attempted":"true","agency_code":"PL 160.15(2)"},{"category":"F","counts":1,"description":"BURGLARY IN THE SECOND DEGREE (DQO)","attempted":"false","agency_code":"PL 140.25(2)"},{"category":"F","counts":1,"description":"CRIMINAL POSSESSION OF A WEAPON IN THE SECOND DEGREE (DQO)","attempted":"false","agency_code":"PL 265.03(1)(B)"},{"category":"F","counts":1,"description":"CRIMINAL POSSESSION OF A WEAPON IN THE SECOND DEGREE (DQO)","attempted":"false","agency_code":"PL 265.03(3)"},{"category":"F","counts":1,"description":"ROBBERY IN THE THIRD DEGREE (DQO)","attempted":"true","agency_code":"PL 160.05"},{"category":"F","counts":1,"description":"CRIMINAL IMPERSONATION IN THE FIRST DEGREE (DQO)","attempted":"false","agency_code":"PL 190.26(1)"},{"category":"M","counts":3,"description":"MENACING IN THE SECOND DEGREE (DQO)","attempted":"false","agency_code":"PL 120.14(1)"},{"category":"M","counts":1,"description":"UNLAWFUL IMPRISONMENT IN THE SECOND DEGREE (DQO)","attempted":"false","agency_code":"PL 135.05"},{"category":"M","counts":1,"description":"CRIMINAL TRESPASS IN THE SECOND DEGREE","attempted":"false","agency_code":"PL 140.15(1)"},{"category":"M","counts":1,"description":"PETIT LARCENY(DQO)","attempted":"false","agency_code":"PL 155.25"},{"category":"M","counts":1,"description":"CRIMINAL IMPERSONATION IN THE SECOND DEGREE","attempted":"false","agency_code":"PL 190.25(3)"},{"category":"M","counts":1,"description":"CRIMINAL POSSESSION OF A WEAPON IN THE FOURTH DEGREE","attempted":"false","agency_code":"PL 265.01(1)"},{"category":"M","counts":3,"description":"MENACING IN THE THIRD DEGREE(DQO)","attempted":"false","agency_code":"PL 120.15"},{"category":"V","counts":3,"description":"HARASSMENT IN THE SECOND DEGREE","attempted":"false","agency_code":"PL 240.26(1)"}],[{"category":"M","counts":1,"description":"CRIMINAL TRESPASS IN THE SECOND DEGREE","attempted":"false","agency_code":"PL 140.15(1)"},{"category":"M","counts":1,"description":"CRIMINAL TRESPASS IN THE THIRD DEGREE","attempted":"false","agency_code":"PL 140.10(A)"},{"category":"V","counts":1,"description":"TRESPASS","attempted":"false","agency_code":"PL 140.05"}],[{"category":"M","counts":1,"description":"ASSAULT IN THE THIRD DEGREE (DQO)","attempted":"false","agency_code":"PL 120.00(1)"},{"category":"M","counts":1,"description":"ASSAULT IN THE THIRD DEGREE (DQO)","attempted":"true","agency_code":"PL 120.00(1)"},{"category":"M","counts":1,"description":"MENACING IN THE THIRD DEGREE(DQO)","attempted":"false","agency_code":"PL 120.15"},{"category":"V","counts":1,"description":"HARASSMENT IN THE SECOND DEGREE","attempted":"false","agency_code":"PL 240.26(1)"}],[{"category":"F","counts":1,"description":"ASSAULT IN THE SECOND DEGREE (DQO)","attempted":"false","agency_code":"PL 120.05(2)"},{"category":"F","counts":1,"description":"ASSAULT IN THE SECOND DEGREE (DQO)","attempted":"false","agency_code":"PL 120.05(3)"},{"category":"F","counts":1,"description":"ASSAULT IN THE SECOND DEGREE (DQO)","attempted":"false","agency_code":"PL 120.05(3)"},{"category":"M","counts":1,"description":"ASSAULT IN THE THIRD DEGREE (DQO)","attempted":"false","agency_code":"PL 120.00(1)"},{"category":"M","counts":1,"description":"ASSAULT IN THE THIRD DEGREE (DQO)","attempted":"false","agency_code":"PL 120.00(2)"},{"category":"M","counts":1,"description":"OBSTRUCTING GOVERNMENTAL ADMINISTRATION IN THE SECOND DEGREE","attempted":"false","agency_code":"PL 195.05"},{"category":"M","counts":1,"description":"OBSTRUCTING GOVERNMENTAL ADMINISTRATION IN THE SECOND DEGREE","attempted":"false","agency_code":"PL 195.05"},{"category":"M","counts":1,"description":"RESISTING ARREST","attempted":"false","agency_code":"PL 205.30"},{"category":"M","counts":1,"description":"RESISTING ARREST","attempted":"false","agency_code":"PL 205.30"},{"category":"M","counts":1,"description":"CRIMINAL POSSESSION OF A WEAPON IN THE FOURTH DEGREE","attempted":"false","agency_code":"PL 265.01(2)"},{"category":"M","counts":1,"description":"MENACING IN THE THIRD DEGREE(DQO)","attempted":"false","agency_code":"PL 120.15"},{"category":"M","counts":1,"description":"MENACING IN THE THIRD DEGREE(DQO)","attempted":"false","agency_code":"PL 120.15"},{"category":"V","counts":1,"description":"HARASSMENT IN THE SECOND DEGREE","attempted":"false","agency_code":"PL 240.26(1)"},{"category":"V","counts":1,"description":"HARASSMENT IN THE SECOND DEGREE","attempted":"false","agency_code":"PL 240.26(1)"}],[{"category":"F","counts":1,"description":"ASSAULT IN THE SECOND DEGREE (DQO)","attempted":"false","agency_code":"PL 120.05(2)"},{"category":"F","counts":1,"description":"ASSAULT IN THE SECOND DEGREE (DQO)","attempted":"false","agency_code":"PL 120.05(3)"},{"category":"F","counts":1,"description":"ASSAULT IN THE SECOND DEGREE (DQO)","attempted":"false","agency_code":"PL 120.05(3)"},{"category":"M","counts":1,"description":"ASSAULT IN THE THIRD DEGREE (DQO)","attempted":"false","agency_code":"PL 120.00(1)"},{"category":"M","counts":1,"description":"ASSAULT IN THE THIRD DEGREE (DQO)","attempted":"false","agency_code":"PL 120.00(2)"},{"category":"M","counts":1,"description":"OBSTRUCTING GOVERNMENTAL ADMINISTRATION IN THE SECOND DEGREE","attempted":"false","agency_code":"PL 195.05"},{"category":"M","counts":1,"description":"OBSTRUCTING GOVERNMENTAL ADMINISTRATION IN THE SECOND DEGREE","attempted":"false","agency_code":"PL 195.05"},{"category":"M","counts":1,"description":"RESISTING ARREST","attempted":"false","agency_code":"PL 205.30"},{"category":"M","counts":1,"description":"RESISTING ARREST","attempted":"false","agency_code":"PL 205.30"},{"category":"M","counts":1,"description":"CRIMINAL POSSESSION OF A WEAPON IN THE FOURTH DEGREE","attempted":"false","agency_code":"PL 265.01(2)"},{"category":"M","counts":1,"description":"MENACING IN THE THIRD DEGREE(DQO)","attempted":"false","agency_code":"PL 120.15"},{"category":"M","counts":1,"description":"MENACING IN THE THIRD DEGREE(DQO)","attempted":"false","agency_code":"PL 120.15"},{"category":"V","counts":1,"description":"HARASSMENT IN THE SECOND DEGREE","attempted":"false","agency_code":"PL 240.26(1)"},{"category":"V","counts":1,"description":"HARASSMENT IN THE SECOND DEGREE","attempted":"false","agency_code":"PL 240.26(1)"}],[{"category":"M","counts":1,"description":"ASSAULT IN THE THIRD DEGREE (DQO)","attempted":"false","agency_code":"PL 120.00(1)"},{"category":"M","counts":1,"description":"ASSAULT IN THE THIRD DEGREE (DQO)","attempted":"true","agency_code":"PL 120.00(1)"},{"category":"M","counts":1,"description":"MENACING IN THE THIRD DEGREE(DQO)","attempted":"false","agency_code":"PL 120.15"},{"category":"V","counts":1,"description":"HARASSMENT IN THE SECOND DEGREE","attempted":"false","agency_code":"PL 240.26(1)"}],[{"category":"M","counts":1,"description":"AGGRAVATED HARASSMENT IN THE SECOND DEGREE","attempted":"false","agency_code":"PL 240.30(4)"},{"category":"M","counts":1,"description":"MENACING IN THE THIRD DEGREE(DQO)","attempted":"false","agency_code":"PL 120.15"},{"category":"M","counts":1,"description":"OVERDRIVING, TORTURING AND INJURING ANIMALS AND FAILURE TO PROVIDE PROPER SUSTENANCE FOR ANIMALS","attempted":"false","agency_code":"AM 353"},{"category":"V","counts":1,"description":"HARASSMENT IN THE SECOND DEGREE","attempted":"false","agency_code":"PL 240.26(1)"}],[{"category":"M","counts":1,"description":"OBSTRUCTING GOVERNMENTAL ADMINISTRATION IN THE SECOND DEGREE","attempted":"false","agency_code":"PL 195.05"},{"category":"M","counts":1,"description":"OBSTRUCTING GOVERNMENTAL ADMINISTRATION IN THE SECOND DEGREE","attempted":"false","agency_code":"PL 195.05"},{"category":"M","counts":1,"description":"RESISTING ARREST","attempted":"false","agency_code":"PL 205.30"}],[{"category":"M","counts":1,"description":"OBSTRUCTING GOVERNMENTAL ADMINISTRATION IN THE SECOND DEGREE","attempted":"false","agency_code":"PL 195.05"},{"category":"M","counts":1,"description":"OBSTRUCTING GOVERNMENTAL ADMINISTRATION IN THE SECOND DEGREE","attempted":"false","agency_code":"PL 195.05"},{"category":"M","counts":1,"description":"RESISTING ARREST","attempted":"false","agency_code":"PL 205.30"}],[{"category":"M","counts":1,"description":"PETIT LARCENY(DQO)","attempted":"false","agency_code":"PL 155.25"},{"category":"M","counts":1,"description":"CRIMINAL POSSESSION OF STOLEN PROPERTY IN THE FIFTH DEGREE","attempted":"false","agency_code":"PL 165.40"}],[{"category":"M","counts":1,"description":"THEFT OF SERVICES","attempted":"false","agency_code":"PL 165.15(3)"}],[{"category":"V","counts":1,"description":"RESTRICTED AREAS AND ACTIVITIES","attempted":"false","agency_code":"RR 1050(9)(D)"}],[{"category":"M","counts":1,"description":"CRIMINAL POSSESSION OF MARIHUANA IN THE FIFTH DEGREE","attempted":"false","agency_code":"PL 221.10(1)"},{"category":"V","counts":1,"description":"UNLAWFUL POSSESSION OF MARIHUANA","attempted":"false","agency_code":"PL 221.05"}],[{"category":"M","counts":1,"description":"THEFT OF SERVICES","attempted":"false","agency_code":"PL 165.15(3)"}],[{"category":"V","counts":1,"description":"UNLAWFUL POSSESSION OF MARIHUANA","attempted":"false","agency_code":"PL 221.05"},{"category":"V","counts":1,"description":"CONSUMPTION OF ALCOHOL IN PUBLIC","attempted":"false","agency_code":"AC 10-125(B)"}],[{"category":"V","counts":1,"description":"CONSUMPTION OF ALCOHOL IN PUBLIC","attempted":"false","agency_code":"AC 10-125(B)"}],[{"category":"M","counts":1,"description":"THEFT OF SERVICES","attempted":"false","agency_code":"PL 165.15(3)"}],[{"category":"M","counts":1,"description":"THEFT OF SERVICES","attempted":"false","agency_code":"PL 165.15(3)"}],[{"category":"M","counts":1,"description":"THEFT OF SERVICES","attempted":"false","agency_code":"PL 165.15(3)"}],[{"category":"V","counts":1,"description":"THROWING OR DROPPING OFFENSIVE MATTERS INTO STREETS AND PUBLIC PLACES","attempted":"false","agency_code":"HC 153.09"}],[{"category":"V","counts":1,"description":"RESTRICTED AREAS AND ACTIVITIES","attempted":"false","agency_code":"RR 1050(9)(D)"}],[{"category":"F","counts":1,"description":"ASSAULT IN THE SECOND DEGREE (DQO)","attempted":"false","agency_code":"PL 120.05(1)"},{"category":"M","counts":1,"description":"ASSAULT IN THE THIRD DEGREE (DQO)","attempted":"false","agency_code":"PL 120.00(1)"},{"category":"M","counts":1,"description":"MENACING IN THE THIRD DEGREE(DQO)","attempted":"false","agency_code":"PL 120.15"},{"category":"V","counts":1,"description":"HARASSMENT IN THE SECOND DEGREE","attempted":"false","agency_code":"PL 240.26(1)"}],[{"category":"F","counts":1,"description":"ASSAULT IN THE SECOND DEGREE (DQO)","attempted":"false","agency_code":"PL 120.05(1)"},{"category":"M","counts":1,"description":"ASSAULT IN THE THIRD DEGREE (DQO)","attempted":"false","agency_code":"PL 120.00(1)"},{"category":"M","counts":1,"description":"MENACING IN THE THIRD DEGREE(DQO)","attempted":"false","agency_code":"PL 120.15"},{"category":"V","counts":1,"description":"HARASSMENT IN THE SECOND DEGREE","attempted":"false","agency_code":"PL 240.26(1)"}],[{"category":"M","counts":1,"description":"LOITERING FOR THE PURPOSE OF ENGAGING IN A PROSTITUTION OFFENSE","attempted":"false","agency_code":"PL 240.37(2)"}],[{"category":"M","counts":1,"description":"THEFT OF SERVICES","attempted":"false","agency_code":"PL 165.15(3)"}],[{"category":"M","counts":1,"description":"ASSAULT IN THE THIRD DEGREE (DQO)","attempted":"false","agency_code":"PL 120.00(1)"},{"category":"M","counts":1,"description":"MENACING IN THE SECOND DEGREE (DQO)","attempted":"false","agency_code":"PL 120.14(1)"},{"category":"M","counts":1,"description":"CRIMINAL POSSESSION OF A WEAPON IN THE FOURTH DEGREE","attempted":"false","agency_code":"PL 265.01(2)"},{"category":"M","counts":1,"description":"ASSAULT IN THE THIRD DEGREE (DQO)","attempted":"true","agency_code":"PL 120.00(1)"},{"category":"M","counts":1,"description":"MENACING IN THE THIRD DEGREE(DQO)","attempted":"false","agency_code":"PL 120.15"},{"category":"V","counts":1,"description":"HARASSMENT IN THE SECOND DEGREE","attempted":"false","agency_code":"PL 240.26(1)"}],[{"category":"M","counts":1,"description":"CRIMINALLY USING DRUG PARAPHERNALIA IN THE SECOND DEGREE","attempted":"false","agency_code":"PL 220.50(3)"},{"category":"M","counts":1,"description":"CRIMINAL POSSESSION OF MARIHUANA IN THE FOURTH DEGREE","attempted":"false","agency_code":"PL 221.15"},{"category":"V","counts":1,"description":"UNLAWFUL POSSESSION OF MARIHUANA","attempted":"false","agency_code":"PL 221.05"}],[{"category":"M","counts":1,"description":"ASSAULT IN THE THIRD DEGREE (DQO)","attempted":"false","agency_code":"PL 120.00(1)"},{"category":"M","counts":1,"description":"CRIMINAL MISCHIEF IN THE FOURTH DEGREE","attempted":"false","agency_code":"PL 145.00(4)"},{"category":"M","counts":1,"description":"ASSAULT IN THE THIRD DEGREE (DQO)","attempted":"true","agency_code":"PL 120.00(1)"},{"category":"M","counts":1,"description":"MENACING IN THE THIRD DEGREE(DQO)","attempted":"false","agency_code":"PL 120.15"},{"category":"V","counts":1,"description":"HARASSMENT IN THE SECOND DEGREE","attempted":"false","agency_code":"PL 240.26(1)"}],[{"category":"M","counts":1,"description":"THEFT OF SERVICES","attempted":"false","agency_code":"PL 165.15(3)"},{"category":"V","counts":1,"description":"TRESPASS","attempted":"false","agency_code":"PL 140.05"},{"category":"V","counts":1,"description":"UNLAWFUL POSSESSION OF MARIHUANA","attempted":"false","agency_code":"PL 221.05"}],[{"category":"F","counts":1,"description":"ASSAULT IN THE SECOND DEGREE (DQO)","attempted":"false","agency_code":"PL 120.05(1)"},{"category":"M","counts":1,"description":"ASSAULT IN THE THIRD DEGREE (DQO)","attempted":"false","agency_code":"PL 120.00(1)"},{"category":"M","counts":1,"description":"MENACING IN THE THIRD DEGREE(DQO)","attempted":"false","agency_code":"PL 120.15"},{"category":"V","counts":1,"description":"HARASSMENT IN THE SECOND DEGREE","attempted":"false","agency_code":"PL 240.26(1)"}],[{"category":"F","counts":1,"description":"ASSAULT IN THE SECOND DEGREE (DQO)","attempted":"false","agency_code":"PL 120.05(1)"},{"category":"M","counts":1,"description":"ASSAULT IN THE THIRD DEGREE (DQO)","attempted":"false","agency_code":"PL 120.00(1)"},{"category":"M","counts":1,"description":"MENACING IN THE THIRD DEGREE(DQO)","attempted":"false","agency_code":"PL 120.15"},{"category":"V","counts":1,"description":"HARASSMENT IN THE SECOND DEGREE","attempted":"false","agency_code":"PL 240.26(1)"}],[{"category":"F","counts":1,"description":"CRIMINAL MISCHIEF IN THE SECOND DEGREE (DQO)","attempted":"false","agency_code":"PL 145.10"},{"category":"F","counts":1,"description":"ASSAULT IN THE SECOND DEGREE (DQO)","attempted":"true","agency_code":"PL 120.05(2)"},{"category":"F","counts":1,"description":"CRIMINAL MISCHIEF IN THE THIRD DEGREE (DQO)","attempted":"false","agency_code":"PL 145.05(2)"},{"category":"M","counts":1,"description":"MENACING IN THE SECOND DEGREE (DQO)","attempted":"false","agency_code":"PL 120.14(1)"},{"category":"M","counts":1,"description":"CRIMINAL MISCHIEF IN THE FOURTH DEGREE","attempted":"false","agency_code":"PL 145.00(1)"},{"category":"M","counts":1,"description":"CRIMINAL POSSESSION OF A WEAPON IN THE FOURTH DEGREE","attempted":"false","agency_code":"PL 265.01(2)"},{"category":"M","counts":1,"description":"ASSAULT IN THE THIRD DEGREE (DQO)","attempted":"true","agency_code":"PL 120.00(1)"},{"category":"M","counts":1,"description":"MENACING IN THE THIRD DEGREE(DQO)","attempted":"false","agency_code":"PL 120.15"},{"category":"V","counts":1,"description":"HARASSMENT IN THE SECOND DEGREE","attempted":"false","agency_code":"PL 240.26(1)"}],[{"category":"M","counts":1,"description":"CRIMINAL CONTEMPT IN THE SECOND DEGREE","attempted":"false","agency_code":"PL 215.50(3)"}],[{"category":"F","counts":1,"description":"ROBBERY IN THE SECOND DEGREE (DQO)","attempted":"false","agency_code":"PL 160.10(1)"},{"category":"F","counts":1,"description":"GRAND LARCENY IN THE FOURTH DEGREE (DQO)","attempted":"false","agency_code":"PL 155.30(5)"},{"category":"M","counts":1,"description":"CRIMINAL POSSESSION OF STOLEN PROPERTY IN THE FIFTH DEGREE","attempted":"false","agency_code":"PL 165.40"}],[{"category":"M","counts":1,"description":"CRIMINAL POSSESSION OF STOLEN PROPERTY IN THE FIFTH DEGREE","attempted":"false","agency_code":"PL 165.40"},{"category":"M","counts":1,"description":"CRIMINAL POSSESSION OF A FORGED INSTRUMENT IN THE THIRD DEGREE","attempted":"false","agency_code":"PL 170.20"},{"category":"M","counts":1,"description":"AGGRAVATED UNLICENSED OPERATION OF A MOTOR VEHICLE IN THE THIRD DEGREE","attempted":"false","agency_code":"VTL 511(1)(A)"},{"category":"M","counts":1,"description":"AGGRAVATED UNLICENSED OPERATION OF A MOTOR VEHICLE IN THE SECOND DEGREE","attempted":"false","agency_code":"VTL 511(2)(A)(IV)"},{"category":"V","counts":1,"description":"UNLICENSED OPERATOR","attempted":"false","agency_code":"VTL 509(1)"},{"category":"I","counts":1,"description":"FAILURE TO HAVE PROOF OF FINANCIAL SECURITY","attempted":"false","agency_code":"VTL 319(1)"},{"category":"I","counts":1,"description":"UNREGISTERED MOTOR VEHICLE","attempted":"false","agency_code":"VTL 401(1)(A)"}],[{"category":"F","counts":1,"description":"CIGARETTE AND TOBACCO PRODUCTS TAX AS AN E FELONY","attempted":"false","agency_code":"TAX 37-1814(B)"},{"category":"M","counts":1,"description":"CRIMINAL POSSESSION OF A FORGED INSTRUMENT IN THE THIRD DEGREE","attempted":"false","agency_code":"PL 170.20"},{"category":"M","counts":1,"description":"ATTEMPT TO EVADE/DEFEAT CIGARETTE TAX","attempted":"false","agency_code":"AC 11-4012(2)(B)"}],[{"category":"M","counts":1,"description":"CRIMINAL POSSESSION OF A WEAPON IN THE FOURTH DEGREE","attempted":"false","agency_code":"PL 265.01(1)"},{"category":"V","counts":1,"description":"UNLAWFUL POSSESSION OF MARIHUANA","attempted":"false","agency_code":"PL 221.05"}],[{"category":"M","counts":1,"description":"CRIMINAL POSSESSION OF MARIHUANA IN THE FIFTH DEGREE","attempted":"false","agency_code":"PL 221.10(1)"},{"category":"V","counts":1,"description":"UNLAWFUL POSSESSION OF MARIHUANA","attempted":"false","agency_code":"PL 221.05"}],[{"category":"M","counts":1,"description":"OPERATION WHILE REGISTRATION OR PRIVILEGE IS SUSPENDED OR REVOKED","attempted":"false","agency_code":"VTL 512"},{"category":"V","counts":1,"description":"UNLAWFUL POSSESSION OF MARIHUANA","attempted":"false","agency_code":"PL 221.05"},{"category":"V","counts":1,"description":"UNLICENSED OPERATOR","attempted":"false","agency_code":"VTL 509(1)"},{"category":"I","counts":1,"description":"FAILURE TO HAVE PROOF OF FINANCIAL SECURITY","attempted":"false","agency_code":"VTL 319(1)"},{"category":"I","counts":1,"description":"IMPROPER DISPLAY OF NUMBER PLATES","attempted":"false","agency_code":"VTL 402(1)"}],[{"category":"M","counts":1,"description":"ASSAULT IN THE THIRD DEGREE (DQO)","attempted":"false","agency_code":"PL 120.00(1)"},{"category":"M","counts":1,"description":"ASSAULT IN THE THIRD DEGREE (DQO)","attempted":"true","agency_code":"PL 120.00(1)"},{"category":"M","counts":1,"description":"MENACING IN THE THIRD DEGREE(DQO)","attempted":"false","agency_code":"PL 120.15"},{"category":"V","counts":1,"description":"HARASSMENT IN THE SECOND DEGREE","attempted":"false","agency_code":"PL 240.26(2)"}],[{"category":"V","counts":1,"description":"DISORDERLY CONDUCT","attempted":"false","agency_code":"PL 240.20(1)"}],[{"category":"F","counts":1,"description":"BURGLARY IN THE FIRST DEGREE (DQO)","attempted":"false","agency_code":"PL 140.30(3)"},{"category":"F","counts":1,"description":"ROBBERY IN THE FIRST DEGREE (DQO)","attempted":"false","agency_code":"PL 160.15(3)"},{"category":"F","counts":1,"description":"BURGLARY IN THE SECOND DEGREE (DQO)","attempted":"false","agency_code":"PL 140.25(1)(C)"},{"category":"F","counts":1,"description":"ROBBERY IN THE SECOND DEGREE (DQO)","attempted":"false","agency_code":"PL 160.10(1)"},{"category":"F","counts":1,"description":"BURGLARY IN THE THIRD DEGREE (DQO)","attempted":"false","agency_code":"PL 140.20"},{"category":"F","counts":1,"description":"ROBBERY IN THE THIRD DEGREE (DQO)","attempted":"false","agency_code":"PL 160.05"},{"category":"F","counts":1,"description":"GRAND LARCENY IN THE FOURTH DEGREE (DQO)","attempted":"false","agency_code":"PL 155.30(5)"},{"category":"M","counts":1,"description":"MENACING IN THE SECOND DEGREE (DQO)","attempted":"false","agency_code":"PL 120.14(1)"},{"category":"M","counts":1,"description":"CRIMINAL TRESPASS IN THE SECOND DEGREE","attempted":"false","agency_code":"PL 140.15(1)"},{"category":"M","counts":1,"description":"POSSESSION OF BURGLAR'S TOOLS(DQO)","attempted":"false","agency_code":"PL 140.35"},{"category":"M","counts":1,"description":"CRIMINAL MISCHIEF IN THE FOURTH DEGREE","attempted":"false","agency_code":"PL 145.00(1)"},{"category":"M","counts":1,"description":"PETIT LARCENY(DQO)","attempted":"false","agency_code":"PL 155.25"},{"category":"M","counts":1,"description":"MENACING IN THE THIRD DEGREE(DQO)","attempted":"false","agency_code":"PL 120.15"},{"category":"M","counts":1,"description":"CRIMINAL TRESPASS IN THE THIRD DEGREE","attempted":"false","agency_code":"PL 140.10(A)"},{"category":"V","counts":1,"description":"TRESPASS","attempted":"false","agency_code":"PL 140.05"},{"category":"V","counts":1,"description":"HARASSMENT IN THE SECOND DEGREE","attempted":"false","agency_code":"PL 240.26(1)"}],[{"category":"F","counts":1,"description":"BURGLARY IN THE FIRST DEGREE (DQO)","attempted":"false","agency_code":"PL 140.30(3)"},{"category":"F","counts":1,"description":"ROBBERY IN THE FIRST DEGREE (DQO)","attempted":"false","agency_code":"PL 160.15(3)"},{"category":"F","counts":1,"description":"BURGLARY IN THE SECOND DEGREE (DQO)","attempted":"false","agency_code":"PL 140.25(1)(C)"},{"category":"F","counts":1,"description":"ROBBERY IN THE SECOND DEGREE (DQO)","attempted":"false","agency_code":"PL 160.10(1)"},{"category":"F","counts":1,"description":"BURGLARY IN THE THIRD DEGREE (DQO)","attempted":"false","agency_code":"PL 140.20"},{"category":"F","counts":1,"description":"ROBBERY IN THE THIRD DEGREE (DQO)","attempted":"false","agency_code":"PL 160.05"},{"category":"F","counts":1,"description":"GRAND LARCENY IN THE FOURTH DEGREE (DQO)","attempted":"false","agency_code":"PL 155.30(5)"},{"category":"M","counts":1,"description":"MENACING IN THE SECOND DEGREE (DQO)","attempted":"false","agency_code":"PL 120.14(1)"},{"category":"M","counts":1,"description":"CRIMINAL TRESPASS IN THE SECOND DEGREE","attempted":"false","agency_code":"PL 140.15(1)"},{"category":"M","counts":1,"description":"POSSESSION OF BURGLAR'S TOOLS(DQO)","attempted":"false","agency_code":"PL 140.35"},{"category":"M","counts":1,"description":"CRIMINAL MISCHIEF IN THE FOURTH DEGREE","attempted":"false","agency_code":"PL 145.00(1)"},{"category":"M","counts":1,"description":"PETIT LARCENY(DQO)","attempted":"false","agency_code":"PL 155.25"},{"category":"M","counts":1,"description":"MENACING IN THE THIRD DEGREE(DQO)","attempted":"false","agency_code":"PL 120.15"},{"category":"M","counts":1,"description":"CRIMINAL TRESPASS IN THE THIRD DEGREE","attempted":"false","agency_code":"PL 140.10(A)"},{"category":"V","counts":1,"description":"TRESPASS","attempted":"false","agency_code":"PL 140.05"},{"category":"V","counts":1,"description":"HARASSMENT IN THE SECOND DEGREE","attempted":"false","agency_code":"PL 240.26(1)"}],[{"category":"M","counts":1,"description":"OBSTRUCTING GOVERNMENTAL ADMINISTRATION IN THE SECOND DEGREE","attempted":"false","agency_code":"PL 195.05"},{"category":"M","counts":1,"description":"RESISTING ARREST","attempted":"false","agency_code":"PL 205.30"},{"category":"V","counts":1,"description":"DISORDERLY CONDUCT","attempted":"false","agency_code":"PL 240.20(1)"},{"category":"I","counts":1,"description":"IMPROPER OR OBSTRUCTED WINDSHIELD OR SIDE WINDOW","attempted":"false","agency_code":"VTL 375(12-A)(A)"}],[{"category":"M","counts":1,"description":"PROSTITUTION","attempted":"false","agency_code":"PL 230.00"}],[{"category":"M","counts":1,"description":"CRIMINAL TRESPASS IN THE SECOND DEGREE(DQO)","attempted":"false","agency_code":"PL 140.15(1)"},{"category":"V","counts":1,"description":"TRESPASS","attempted":"false","agency_code":"PL 140.05"}],[{"category":"M","counts":1,"description":"RESISTING ARREST","attempted":"false","agency_code":"PL 205.30"},{"category":"V","counts":1,"description":"THROWING OR DROPPING OFFENSIVE MATTERS INTO STREETS AND PUBLIC PLACES","attempted":"false","agency_code":"HC 153.09"}],[{"category":"M","counts":1,"description":"CRIMINAL TRESPASS IN THE SECOND DEGREE(DQO)","attempted":"false","agency_code":"PL 140.15(1)"},{"category":"V","counts":1,"description":"TRESPASS","attempted":"false","agency_code":"PL 140.05"}],[{"category":"M","counts":1,"description":"CRIMINAL TRESPASS IN THE SECOND DEGREE(DQO)","attempted":"false","agency_code":"PL 140.15(1)"},{"category":"V","counts":1,"description":"TRESPASS","attempted":"false","agency_code":"PL 140.05"}],[{"category":"M","counts":1,"description":"CRIMINAL TRESPASS IN THE SECOND DEGREE(DQO)","attempted":"false","agency_code":"PL 140.15(1)"},{"category":"V","counts":1,"description":"TRESPASS","attempted":"false","agency_code":"PL 140.05"}],[{"category":"M","counts":1,"description":"CRIMINAL POSSESSION OF MARIHUANA IN THE FIFTH DEGREE","attempted":"false","agency_code":"PL 221.10(1)"},{"category":"V","counts":1,"description":"UNLAWFUL POSSESSION OF MARIHUANA","attempted":"false","agency_code":"PL 221.05"}],[{"category":"F","counts":1,"description":"CRIMINAL POSSESSION OF A CONTROLLED SUBSTANCE IN THE FIRST DEGREE (DQO)","attempted":"false","agency_code":"PL 220.21(1)"},{"category":"F","counts":2,"description":"CRIMINAL POSSESSION OF A CONTROLLED SUBSTANCE IN THE THIRD DEGREE (DQO)","attempted":"false","agency_code":"PL 220.16(1)"},{"category":"F","counts":2,"description":"CRIMINAL POSSESSION OF A CONTROLLED SUBSTANCE IN THE FIFTH DEGREE (DQO)","attempted":"false","agency_code":"PL 220.06(1)"},{"category":"M","counts":4,"description":"CRIMINAL POSSESSION OF A CONTROLLED SUBSTANCE IN THE SEVENTH DEGREE","attempted":"false","agency_code":"PL 220.03"},{"category":"M","counts":1,"description":"CRIMINAL POSSESSION OF A WEAPON IN THE FOURTH DEGREE","attempted":"false","agency_code":"PL 265.01(1)"},{"category":"M","counts":1,"description":"CRIMINAL POSSESSION OF MARIHUANA IN THE FIFTH DEGREE","attempted":"false","agency_code":"PL 221.10(2)"},{"category":"V","counts":1,"description":"UNLAWFUL POSSESSION OF MARIHUANA","attempted":"false","agency_code":"PL 221.05"}],[{"category":"F","counts":1,"description":"CRIMINAL POSSESSION OF A CONTROLLED SUBSTANCE IN THE FIRST DEGREE (DQO)","attempted":"false","agency_code":"PL 220.21(1)"},{"category":"F","counts":2,"description":"CRIMINAL POSSESSION OF A CONTROLLED SUBSTANCE IN THE THIRD DEGREE (DQO)","attempted":"false","agency_code":"PL 220.16(1)"},{"category":"F","counts":2,"description":"CRIMINAL POSSESSION OF A CONTROLLED SUBSTANCE IN THE FIFTH DEGREE (DQO)","attempted":"false","agency_code":"PL 220.06(1)"},{"category":"M","counts":4,"description":"CRIMINAL POSSESSION OF A CONTROLLED SUBSTANCE IN THE SEVENTH DEGREE","attempted":"false","agency_code":"PL 220.03"},{"category":"M","counts":1,"description":"CRIMINAL POSSESSION OF A WEAPON IN THE FOURTH DEGREE","attempted":"false","agency_code":"PL 265.01(1)"},{"category":"M","counts":1,"description":"CRIMINAL POSSESSION OF MARIHUANA IN THE FIFTH DEGREE","attempted":"false","agency_code":"PL 221.10(2)"},{"category":"V","counts":1,"description":"UNLAWFUL POSSESSION OF MARIHUANA","attempted":"false","agency_code":"PL 221.05"}],[{"category":"M","counts":1,"description":"CRIMINAL TRESPASS IN THE SECOND DEGREE","attempted":"false","agency_code":"PL 140.15(1)"},{"category":"M","counts":1,"description":"CRIMINAL TRESPASS IN THE THIRD DEGREE","attempted":"false","agency_code":"PL 140.10(A)"},{"category":"V","counts":1,"description":"TRESPASS","attempted":"false","agency_code":"PL 140.05"}],[{"category":"M","counts":1,"description":"CRIMINAL TRESPASS IN THE SECOND DEGREE","attempted":"false","agency_code":"PL 140.15(1)"},{"category":"M","counts":1,"description":"CRIMINAL TRESPASS IN THE THIRD DEGREE","attempted":"false","agency_code":"PL 140.10(A)"},{"category":"V","counts":1,"description":"TRESPASS","attempted":"false","agency_code":"PL 140.05"}],[{"category":"M","counts":1,"description":"ASSAULT IN THE THIRD DEGREE (DQO)","attempted":"false","agency_code":"PL 120.00(1)"},{"category":"M","counts":1,"description":"ASSAULT IN THE THIRD DEGREE (DQO)","attempted":"true","agency_code":"PL 120.00(1)"},{"category":"M","counts":1,"description":"MENACING IN THE THIRD DEGREE(DQO)","attempted":"false","agency_code":"PL 120.15"},{"category":"V","counts":1,"description":"HARASSMENT IN THE SECOND DEGREE","attempted":"false","agency_code":"PL 240.26(1)"}],[{"category":"M","counts":1,"description":"OBSTRUCTING GOVERNMENTAL ADMINISTRATION IN THE SECOND DEGREE","attempted":"false","agency_code":"PL 195.05"}],[{"category":"M","counts":1,"description":"CRIMINAL POSSESSION OF A CONTROLLED SUBSTANCE IN THE SEVENTH DEGREE","attempted":"false","agency_code":"PL 220.03"},{"category":"M","counts":1,"description":"OBSTRUCTING GOVERNMENTAL ADMINISTRATION IN THE SECOND DEGREE","attempted":"false","agency_code":"PL 195.05"},{"category":"M","counts":1,"description":"MENACING IN THE THIRD DEGREE(DQO)","attempted":"false","agency_code":"PL 120.15"},{"category":"V","counts":1,"description":"DISORDERLY CONDUCT","attempted":"false","agency_code":"PL 240.20(1)"},{"category":"V","counts":1,"description":"HARASSMENT IN THE SECOND DEGREE","attempted":"false","agency_code":"PL 240.26(1)"}],[{"category":"M","counts":1,"description":"CRIMINAL CONTEMPT IN THE SECOND DEGREE","attempted":"false","agency_code":"PL 215.50(3)"},{"category":"M","counts":1,"description":"CRIMINAL CONTEMPT IN THE SECOND DEGREE","attempted":"false","agency_code":"PL 215.50(3)"}],[{"category":"F","counts":1,"description":"ROBBERY IN THE SECOND DEGREE (DQO)","attempted":"true","agency_code":"PL 160.10(1)"},{"category":"F","counts":1,"description":"ROBBERY IN THE SECOND DEGREE (DQO)","attempted":"true","agency_code":"PL 160.10(2)(A)"},{"category":"F","counts":1,"description":"ASSAULT IN THE SECOND DEGREE (DQO)","attempted":"false","agency_code":"PL 120.05(6)"},{"category":"F","counts":1,"description":"ROBBERY IN THE THIRD DEGREE (DQO)","attempted":"true","agency_code":"PL 160.05"},{"category":"M","counts":1,"description":"ASSAULT IN THE THIRD DEGREE (DQO)","attempted":"false","agency_code":"PL 120.00(1)"},{"category":"M","counts":1,"description":"MENACING IN THE THIRD DEGREE(DQO)","attempted":"false","agency_code":"PL 120.15"},{"category":"V","counts":1,"description":"HARASSMENT IN THE SECOND DEGREE","attempted":"false","agency_code":"PL 240.26(1)"}],[{"category":"F","counts":1,"description":"ROBBERY IN THE SECOND DEGREE (DQO)","attempted":"true","agency_code":"PL 160.10(1)"},{"category":"F","counts":1,"description":"ROBBERY IN THE SECOND DEGREE (DQO)","attempted":"true","agency_code":"PL 160.10(2)(A)"},{"category":"F","counts":1,"description":"ASSAULT IN THE SECOND DEGREE (DQO)","attempted":"false","agency_code":"PL 120.05(6)"},{"category":"F","counts":1,"description":"ROBBERY IN THE THIRD DEGREE (DQO)","attempted":"true","agency_code":"PL 160.05"},{"category":"M","counts":1,"description":"ASSAULT IN THE THIRD DEGREE (DQO)","attempted":"false","agency_code":"PL 120.00(1)"},{"category":"M","counts":1,"description":"MENACING IN THE THIRD DEGREE(DQO)","attempted":"false","agency_code":"PL 120.15"},{"category":"V","counts":1,"description":"HARASSMENT IN THE SECOND DEGREE","attempted":"false","agency_code":"PL 240.26(1)"}],[{"category":"M","counts":1,"description":"PROSTITUTION","attempted":"false","agency_code":"PL 230.00"}],[{"category":"M","counts":1,"description":"OBSTRUCTING GOVERNMENTAL ADMINISTRATION IN THE SECOND DEGREE","attempted":"false","agency_code":"PL 195.05"},{"category":"M","counts":1,"description":"RESISTING ARREST","attempted":"false","agency_code":"PL 205.30"},{"category":"V","counts":1,"description":"DISORDERLY CONDUCT","attempted":"false","agency_code":"PL 240.20(1)"},{"category":"V","counts":1,"description":"DISORDERLY CONDUCT","attempted":"false","agency_code":"PL 240.20(2)"},{"category":"I","counts":1,"description":"IMPROPER OR NO HEADLIGHTS","attempted":"false","agency_code":"VTL 375(2)(A)(1)"}],[{"category":"F","counts":1,"description":"CRIMINAL POSSESSION OF A CONTROLLED SUBSTANCE IN THE THIRD DEGREE (DQO)","attempted":"false","agency_code":"PL 220.16(1)"},{"category":"F","counts":1,"description":"CRIMINAL POSSESSION OF A CONTROLLED SUBSTANCE IN THE FIFTH DEGREE (DQO)","attempted":"false","agency_code":"PL 220.06(1)"},{"category":"M","counts":3,"description":"CRIMINAL POSSESSION OF A CONTROLLED SUBSTANCE IN THE SEVENTH DEGREE","attempted":"false","agency_code":"PL 220.03"}],[{"category":"M","counts":1,"description":"OPERATING A MOTOR VEHICLE WHILE UNDER THE INFLUENCE OF ALCOHOL OR DRUGS","attempted":"false","agency_code":"VTL 1192(2)"},{"category":"M","counts":1,"description":"OPERATING A MOTOR VEHICLE WHILE UNDER THE INFLUENCE OF ALCOHOL OR DRUGS","attempted":"false","agency_code":"VTL 1192(3)"},{"category":"M","counts":1,"description":"CIRCUMVENTION OF INTERLOCK DEVICE","attempted":"false","agency_code":"VTL 1198(9)(C)"},{"category":"M","counts":1,"description":"OPERATING A MOTOR VEHICLE AFTER HAVING CONSUMED ALCOHOL AND BEING UNDER THE AGE OF TWENTY-ONE","attempted":"false","agency_code":"VTL 1192(A)"},{"category":"V","counts":1,"description":"FAILURE TO GIVE APPROPRIATE SIGNAL TO TURN","attempted":"false","agency_code":"VTL 1163(A)"}],[{"category":"M","counts":1,"description":"CRIMINAL POSSESSION OF A CONTROLLED SUBSTANCE IN THE SEVENTH DEGREE","attempted":"false","agency_code":"PL 220.03"},{"category":"M","counts":1,"description":"CRIMINAL POSSESSION OF MARIHUANA IN THE FIFTH DEGREE","attempted":"false","agency_code":"PL 221.10(1)"},{"category":"V","counts":1,"description":"UNLAWFUL POSSESSION OF MARIHUANA","attempted":"false","agency_code":"PL 221.05"},{"category":"I","counts":1,"description":"CONSUMPTION OR POSSESSION OF ALCOHOLIC BEVERAGES IN CERTAIN MOTOR VEHICLES","attempted":"false","agency_code":"VTL 1227(1)"}],[{"category":"M","counts":1,"description":"OBSTRUCTING GOVERNMENTAL ADMINISTRATION IN THE SECOND DEGREE","attempted":"false","agency_code":"PL 195.05"},{"category":"M","counts":1,"description":"RESISTING ARREST","attempted":"false","agency_code":"PL 205.30"},{"category":"M","counts":1,"description":"UNLAWFUL ASSEMBLY","attempted":"false","agency_code":"PL 240.10"},{"category":"V","counts":1,"description":"DISORDERLY CONDUCT","attempted":"false","agency_code":"PL 240.20(1)"},{"category":"V","counts":1,"description":"DISORDERLY CONDUCT","attempted":"false","agency_code":"PL 240.20(2)"},{"category":"V","counts":1,"description":"DISORDERLY CONDUCT","attempted":"false","agency_code":"PL 240.20(3)"},{"category":"V","counts":1,"description":"DISORDERLY CONDUCT","attempted":"false","agency_code":"PL 240.20(6)"}],[{"category":"M","counts":1,"description":"CRIMINAL TRESPASS IN THE SECOND DEGREE","attempted":"false","agency_code":"PL 140.15(1)"},{"category":"M","counts":1,"description":"RESISTING ARREST","attempted":"false","agency_code":"PL 205.30"},{"category":"M","counts":1,"description":"MENACING IN THE THIRD DEGREE(DQO)","attempted":"false","agency_code":"PL 120.15"},{"category":"V","counts":1,"description":"TRESPASS","attempted":"false","agency_code":"PL 140.05"},{"category":"V","counts":1,"description":"DISORDERLY CONDUCT","attempted":"false","agency_code":"PL 240.20(1)"},{"category":"V","counts":1,"description":"HARASSMENT IN THE SECOND DEGREE","attempted":"false","agency_code":"PL 240.26(1)"}],[{"category":"M","counts":1,"description":"UNLAWFUL ASSEMBLY","attempted":"false","agency_code":"PL 240.10"},{"category":"V","counts":1,"description":"DISORDERLY CONDUCT","attempted":"false","agency_code":"PL 240.20(1)"},{"category":"V","counts":1,"description":"DISORDERLY CONDUCT","attempted":"false","agency_code":"PL 240.20(2)"},{"category":"V","counts":1,"description":"DISORDERLY CONDUCT","attempted":"false","agency_code":"PL 240.20(3)"},{"category":"V","counts":1,"description":"DISORDERLY CONDUCT","attempted":"false","agency_code":"PL 240.20(6)"}],[{"category":"M","counts":1,"description":"OPERATING A MOTOR VEHICLE WHILE UNDER THE INFLUENCE OF ALCOHOL OR DRUGS","attempted":"false","agency_code":"VTL 1192(2)"},{"category":"M","counts":1,"description":"OPERATING A MOTOR VEHICLE WHILE UNDER THE INFLUENCE OF ALCOHOL OR DRUGS","attempted":"false","agency_code":"VTL 1192(3)"},{"category":"V","counts":1,"description":"FAILURE TO GIVE APPROPRIATE SIGNAL TO TURN","attempted":"false","agency_code":"VTL 1163(A)"},{"category":"I","counts":1,"description":"TURNING MOVEMENTS AND REQUIRED SIGNALS","attempted":"false","agency_code":"VTL 1163(D)"},{"category":"I","counts":1,"description":"OPERATING A MOTOR VEHICLE WHILE UNDER THE INFLUENCE OF ALCOHOL OR DRUGS","attempted":"false","agency_code":"VTL 1192(1)"}],[{"category":"M","counts":1,"description":"ASSAULT IN THE THIRD DEGREE (DQO)","attempted":"false","agency_code":"PL 120.00(1)"},{"category":"M","counts":1,"description":"CRIMINAL POSSESSION OF A WEAPON IN THE FOURTH DEGREE","attempted":"false","agency_code":"PL 265.01(2)"},{"category":"M","counts":1,"description":"ASSAULT IN THE THIRD DEGREE (DQO)","attempted":"true","agency_code":"PL 120.00(1)"},{"category":"M","counts":1,"description":"MENACING IN THE THIRD DEGREE(DQO)","attempted":"false","agency_code":"PL 120.15"},{"category":"V","counts":1,"description":"HARASSMENT IN THE SECOND DEGREE","attempted":"false","agency_code":"PL 240.26(1)"}],[{"category":"M","counts":1,"description":"ASSAULT IN THE THIRD DEGREE (DQO)","attempted":"false","agency_code":"PL 120.00(1)"},{"category":"M","counts":1,"description":"MENACING IN THE THIRD DEGREE(DQO)","attempted":"false","agency_code":"PL 120.15"},{"category":"V","counts":1,"description":"HARASSMENT IN THE SECOND DEGREE","attempted":"false","agency_code":"PL 240.26(1)"}],[{"category":"M","counts":1,"description":"RESISTING ARREST","attempted":"false","agency_code":"PL 205.30"},{"category":"V","counts":1,"description":"DISORDERLY CONDUCT","attempted":"false","agency_code":"PL 240.20(1)"},{"category":"V","counts":1,"description":"HARASSMENT IN THE SECOND DEGREE","attempted":"false","agency_code":"PL 240.26(1)"}],[{"category":"M","counts":1,"description":"OPERATING A MOTOR VEHICLE WHILE UNDER THE INFLUENCE OF ALCOHOL OR DRUGS","attempted":"false","agency_code":"VTL 1192(2)"},{"category":"M","counts":1,"description":"OPERATING A MOTOR VEHICLE WHILE UNDER THE INFLUENCE OF ALCOHOL OR DRUGS","attempted":"false","agency_code":"VTL 1192(3)"},{"category":"I","counts":1,"description":"OPERATING A MOTOR VEHICLE WHILE UNDER THE INFLUENCE OF ALCOHOL OR DRUGS","attempted":"false","agency_code":"VTL 1192(1)"},{"category":"I","counts":1,"description":"IMPROPER OR NO HEADLIGHTS","attempted":"false","agency_code":"VTL 375(2)(A)(1)"}],[{"category":"M","counts":1,"description":"PROSTITUTION","attempted":"false","agency_code":"PL 230.00"}],[{"category":"M","counts":1,"description":"PROSTITUTION","attempted":"false","agency_code":"PL 230.00"}],[{"category":"M","counts":1,"description":"PROSTITUTION","attempted":"false","agency_code":"PL 230.00"}],[{"category":"M","counts":1,"description":"CRIMINAL POSSESSION OF MARIHUANA IN THE FIFTH DEGREE","attempted":"false","agency_code":"PL 221.10(1)"},{"category":"V","counts":1,"description":"UNLAWFUL POSSESSION OF MARIHUANA","attempted":"false","agency_code":"PL 221.05"}],[{"category":"M","counts":1,"description":"CRIMINAL TRESPASS IN THE SECOND DEGREE(DQO)","attempted":"false","agency_code":"PL 140.15(1)"},{"category":"V","counts":1,"description":"TRESPASS","attempted":"false","agency_code":"PL 140.05"}],[{"category":"M","counts":1,"description":"CRIMINAL TRESPASS IN THE SECOND DEGREE(DQO)","attempted":"false","agency_code":"PL 140.15(1)"},{"category":"V","counts":1,"description":"TRESPASS","attempted":"false","agency_code":"PL 140.05"}],[{"category":"M","counts":1,"description":"CRIMINAL MISCHIEF IN THE FOURTH DEGREE","attempted":"false","agency_code":"PL 145.00(1)"}],[{"category":"M","counts":1,"description":"AGGRAVATED UNLICENSED OPERATION OF A MOTOR VEHICLE IN THE THIRD DEGREE","attempted":"false","agency_code":"VTL 511(1)(A)"},{"category":"M","counts":1,"description":"AGGRAVATED UNLICENSED OPERATION OF A MOTOR VEHICLE IN THE SECOND DEGREE","attempted":"false","agency_code":"VTL 511(2)(A)(IV)"},{"category":"V","counts":1,"description":"UNLICENSED OPERATOR","attempted":"false","agency_code":"VTL 509(1)"},{"category":"I","counts":1,"description":"TURNING MOVEMENTS AND REQUIRED SIGNALS","attempted":"false","agency_code":"VTL 1163(D)"},{"category":"I","counts":1,"description":"FAILURE TO HAVE PROOF OF FINANCIAL SECURITY","attempted":"false","agency_code":"VTL 319(1)"},{"category":"I","counts":1,"description":"UNREGISTERED MOTOR VEHICLE","attempted":"false","agency_code":"VTL 401(1)(A)"}],[{"category":"M","counts":1,"description":"ASSAULT IN THE THIRD DEGREE (DQO)","attempted":"false","agency_code":"PL 120.00(1)"},{"category":"M","counts":1,"description":"MENACING IN THE THIRD DEGREE(DQO)","attempted":"false","agency_code":"PL 120.15"},{"category":"V","counts":1,"description":"HARASSMENT IN THE SECOND DEGREE","attempted":"false","agency_code":"PL 240.26(1)"}],[{"category":"M","counts":1,"description":"CRIMINAL POSSESSION OF A FORGED INSTRUMENT IN THE THIRD DEGREE","attempted":"false","agency_code":"PL 170.20"}],[{"category":"M","counts":1,"description":"CRIMINAL TRESPASS IN THE SECOND DEGREE","attempted":"false","agency_code":"PL 140.15(1)"},{"category":"V","counts":1,"description":"TRESPASS","attempted":"false","agency_code":"PL 140.05"}],[{"category":"M","counts":1,"description":"MENACING IN THE SECOND DEGREE (DQO)","attempted":"false","agency_code":"PL 120.14(1)"},{"category":"M","counts":1,"description":"CRIMINAL POSSESSION OF A WEAPON IN THE FOURTH DEGREE","attempted":"false","agency_code":"PL 265.01(2)"}],[{"category":"M","counts":1,"description":"ASSAULT IN THE THIRD DEGREE (DQO)","attempted":"false","agency_code":"PL 120.00(1)"},{"category":"M","counts":1,"description":"MENACING IN THE THIRD DEGREE(DQO)","attempted":"false","agency_code":"PL 120.15"},{"category":"V","counts":1,"description":"HARASSMENT IN THE SECOND DEGREE","attempted":"false","agency_code":"PL 240.26(1)"}],[{"category":"V","counts":1,"description":"DISORDERLY CONDUCT","attempted":"false","agency_code":"PL 240.20(3)"}],[{"category":"M","counts":1,"description":"MENACING IN THE THIRD DEGREE(DQO)","attempted":"false","agency_code":"PL 120.15"},{"category":"V","counts":1,"description":"HARASSMENT IN THE SECOND DEGREE","attempted":"false","agency_code":"PL 240.26(1)"}],[{"category":"F","counts":1,"description":"Criminal Sale of a Controlled Substance in the Fifth Degree","attempted":"false","agency_code":"PL 220.31"},{"category":"M","counts":1,"description":"Criminal Diversion of Prescription Medications and Prescriptions in the Fourth Degree","attempted":"false","agency_code":"PL 178.10"}],[{"category":"M","counts":1,"description":"Theft of Services","attempted":"false","agency_code":"PL 165.15(3)"},{"category":"M","counts":1,"description":"Criminal Trespass in the Third Degree","attempted":"false","agency_code":"PL 140.10(a)"}],[{"category":"M","counts":1,"description":"Assault in the Third Degree","attempted":"false","agency_code":"PL 120.00(1)"},{"category":"M","counts":1,"description":"Assault in the Third Degree","attempted":"false","agency_code":"PL 120.00(2)"},{"category":"V","counts":1,"description":"Harassment in the Second Degree","attempted":"false","agency_code":"PL 240.26(1)"}],[{"category":"V","counts":1,"description":"Placing a Foot on a Seat on a MTA Subway or Bus","attempted":"false","agency_code":"21 NYCRR 1050.7(j)(2)"}],[{"category":"F","counts":1,"description":"Criminal Sale of a Controlled Substance in the Third Degree","attempted":"false","agency_code":"PL 220.39(1)"}],[{"category":"V","counts":1,"description":"Unlawful Solicitation in the Subway","attempted":"false","agency_code":"21 NYCRR 1050.6(b)(2)"},{"category":"V","counts":1,"description":"Blocking Free Movement in a Transit Facility","attempted":"false","agency_code":"21 NYCRR 1050.7(j)(4)"}],[{"category":"F","counts":1,"description":"Criminal Sale of a Controlled Substance in the Third Degree","attempted":"false","agency_code":"PL 220.39(1)"}],[{"category":"M","counts":1,"description":"Resisting Arrest","attempted":"false","agency_code":"PL 205.30"},{"category":"V","counts":1,"description":"Consumption of Alcohol in a Public Place","attempted":"false","agency_code":"AC 10-125(b)"}],[{"category":"M","counts":1,"description":"Criminal Trespass in the Second Degree","attempted":"false","agency_code":"PL 140.15(1)"},{"category":"M","counts":1,"description":"Criminal Possession of a Controlled Substance in the Seventh Degree","attempted":"false","agency_code":"PL 220.03"}],[{"category":"M","counts":1,"description":"Theft of Services","attempted":"false","agency_code":"PL 165.15(3)"},{"category":"M","counts":1,"description":"Criminal Trespass in the Third Degree","attempted":"false","agency_code":"PL 140.10(a)"}],[{"category":"M","counts":1,"description":"ASSAULT IN THE THIRD DEGREE (DQO)","attempted":"false","agency_code":"PL 120.00(1)"},{"category":"M","counts":1,"description":"CRIMINAL OBSTRUCTION OF BREATHING OR BLOOD CIRCULATION (DQO)","attempted":"false","agency_code":"PL 121.11(A)"},{"category":"M","counts":1,"description":"ASSAULT IN THE THIRD DEGREE (DQO)","attempted":"true","agency_code":"PL 120.00(1)"},{"category":"M","counts":1,"description":"MENACING IN THE THIRD DEGREE(DQO)","attempted":"false","agency_code":"PL 120.15"},{"category":"V","counts":1,"description":"HARASSMENT IN THE SECOND DEGREE","attempted":"false","agency_code":"PL 240.26(1)"}],[{"category":"V","counts":1,"description":"CONSUMPTION OF ALCOHOL IN PUBLIC","attempted":"false","agency_code":"AC 10-125(B)"}],[{"category":"I","counts":1,"description":"RIDING A BICYCLE WHERE PROHIBITED","attempted":"false","agency_code":"VTL 1234-A"}],[{"category":"M","counts":1,"description":"PETIT LARCENY(DQO)","attempted":"false","agency_code":"PL 155.25"},{"category":"M","counts":1,"description":"CRIMINAL POSSESSION OF STOLEN PROPERTY IN THE FIFTH DEGREE","attempted":"false","agency_code":"PL 165.40"}],[{"category":"M","counts":1,"description":"POSSESSION OF BOX CUTTERS IN A PUBLIC PLACE OR ON SCHOOL PREMISES BY PERSONS UNDER TWENTY-TWO YEARS OF AGE","attempted":"false","agency_code":"AC 10-134(1)(E)"}],[{"category":"M","counts":1,"description":"AGGRAVATED UNLICENSED OPERATION OF A MOTOR VEHICLE IN THE THIRD DEGREE","attempted":"false","agency_code":"VTL 511(1)(A)"},{"category":"V","counts":1,"description":"UNLICENSED OPERATOR","attempted":"false","agency_code":"VTL 509(1)"}],[{"category":"M","counts":1,"description":"CRIMINAL POSSESSION OF MARIHUANA IN THE FIFTH DEGREE","attempted":"false","agency_code":"PL 221.10(1)"},{"category":"V","counts":1,"description":"UNLAWFUL POSSESSION OF MARIHUANA","attempted":"false","agency_code":"PL 221.05"}],[{"category":"M","counts":1,"description":"Theft of Services","attempted":"false","agency_code":"PL 165.15(3)"},{"category":"M","counts":1,"description":"Criminal Trespass in the Third Degree","attempted":"false","agency_code":"PL 140.10(a)"}],[{"category":"M","counts":1,"description":"Urinating in a Public Place-Not DNA Eligible","attempted":"false","agency_code":"24 RCNY 153.09"}],[{"category":"M","counts":1,"description":"Criminal Trespass in the Second Degree","attempted":"false","agency_code":"PL 140.15(1)"},{"category":"M","counts":1,"description":"Criminal Trespass in the Third Degree","attempted":"false","agency_code":"PL 140.10(a)"},{"category":"V","counts":1,"description":"Trespass","attempted":"false","agency_code":"PL 140.05"}],[{"category":"M","counts":1,"description":"Criminal Trespass in the Third Degree","attempted":"false","agency_code":"PL 140.10(a)"}],[{"category":"M","counts":1,"description":"Theft of Services","attempted":"false","agency_code":"PL 165.15(3)"},{"category":"M","counts":1,"description":"Criminal Trespass in the Third Degree","attempted":"false","agency_code":"PL 140.10(a)"}],[{"category":"M","counts":1,"description":"MENACING IN THE SECOND DEGREE (DQO)","attempted":"false","agency_code":"PL 120.14(1)"},{"category":"V","counts":1,"description":"HARASSMENT IN THE SECOND DEGREE","attempted":"false","agency_code":"PL 240.26(1)"}],[{"category":"M","counts":1,"description":"ASSAULT IN THE THIRD DEGREE (DQO)","attempted":"false","agency_code":"PL 120.00(1)"},{"category":"M","counts":1,"description":"MENACING IN THE SECOND DEGREE (DQO)","attempted":"false","agency_code":"PL 120.14(1)"},{"category":"M","counts":1,"description":"CRIMINAL POSSESSION OF A WEAPON IN THE FOURTH DEGREE","attempted":"false","agency_code":"PL 265.01(1)"},{"category":"M","counts":1,"description":"ASSAULT IN THE THIRD DEGREE (DQO)","attempted":"true","agency_code":"PL 120.00(1)"},{"category":"M","counts":1,"description":"MENACING IN THE THIRD DEGREE(DQO)","attempted":"false","agency_code":"PL 120.15"},{"category":"V","counts":1,"description":"HARASSMENT IN THE SECOND DEGREE","attempted":"false","agency_code":"PL 240.26(1)"}],[{"category":"F","counts":1,"description":"ASSAULT IN THE SECOND DEGREE (DQO)","attempted":"false","agency_code":"PL 120.05(1)"},{"category":"M","counts":1,"description":"ASSAULT IN THE THIRD DEGREE (DQO)","attempted":"false","agency_code":"PL 120.00(1)"},{"category":"M","counts":1,"description":"MENACING IN THE THIRD DEGREE(DQO)","attempted":"false","agency_code":"PL 120.15"},{"category":"V","counts":1,"description":"HARASSMENT IN THE SECOND DEGREE","attempted":"false","agency_code":"PL 240.26(1)"}],[{"category":"F","counts":1,"description":"CRIMINAL POSSESSION OF A CONTROLLED SUBSTANCE IN THE THIRD DEGREE (DQO)","attempted":"false","agency_code":"PL 220.16(1)"},{"category":"F","counts":1,"description":"CRIMINAL POSSESSION OF A CONTROLLED SUBSTANCE IN THE FIFTH DEGREE (DQO)","attempted":"false","agency_code":"PL 220.06(1)"},{"category":"M","counts":3,"description":"CRIMINAL POSSESSION OF A CONTROLLED SUBSTANCE IN THE SEVENTH DEGREE","attempted":"false","agency_code":"PL 220.03"}],[{"category":"M","counts":1,"description":"CRIMINAL TRESPASS IN THE SECOND DEGREE","attempted":"false","agency_code":"PL 140.15(1)"},{"category":"M","counts":1,"description":"CRIMINAL TRESPASS IN THE THIRD DEGREE","attempted":"false","agency_code":"PL 140.10(A)"},{"category":"V","counts":1,"description":"TRESPASS","attempted":"false","agency_code":"PL 140.05"}]]